<?xml version="1.0" encoding="UTF-8" standalone="no"?>
<transcription xmlns:xsi="http://www.w3.org/2001/XMLSchema-instance" xsi:noNamespaceSchemaLocation="http://www.livesandletters.ac.uk/schema/aor2_18112016.xsd">
    <page filename="RCP10549-50v2.373r.tif" pagination="197" reader="John Dee" signature="Nn.iii."/>   
    <annotation>
        
        <marginalia anchor_text="si impetraritis" hand="Italian">
            <language ident="LA">
                <position book_orientation="0" place="head">
                    <marginalia_text>
                        Si impetraritis
                    </marginalia_text>
                </position>
            </language>
            <translation>
                If you succeed.
            </translation>
        </marginalia>
        
        <marginalia hand="Italian">
            <language ident="LA">
                <position book_orientation="0" place="right_margin">
                    <marginalia_text>
                        Cotta
                    </marginalia_text>
                    <person name="Gaius Aurelius Cotta"/>
                </position>
            </language>
            <translation>
                Gaius Aurelius Cotta.
            </translation>
        </marginalia>
        
        <marginalia hand="Italian">
            <language ident="LA">
                <position book_orientation="0" place="right_margin">
                    <marginalia_text>
                        Academicus
                    </marginalia_text>
                </position>
            </language>
            <translation>
                Academic.
            </translation>
        </marginalia>
        
        <marginalia anchor_text="accubitio, inclinatio, sessio, co[m]prehensio" hand="Italian">
            <language ident="LA">
                <position book_orientation="0" place="head">
                    <marginalia_text>
                        accubitio inclinatio sessio comprehensio 
                    </marginalia_text>
                </position>
            </language>
            <language ident="EN">
                <position book_orientation="0" place="head">
                    <marginalia_text>
                        griping sumwhat.
                    </marginalia_text>
                </position>
            </language>
        </marginalia>
        
        <marginalia hand="Italian">
            <language ident="LA">
                <position book_orientation="0" place="right_margin">
                    <marginalia_text>
                        Cultus &amp; curatio Corporis.
                    </marginalia_text>
                </position>
            </language>
            <translation>
                The care and treatment of the body.
            </translation>
        </marginalia>
        
        <marginalia anchor_text="mares deos &amp; foeminas" hand="Italian">
            <language ident="LA">
                <position book_orientation="0" place="right_margin">
                    <marginalia_text>
                        Mares dij &amp; fo[e]mina[e]
                    </marginalia_text>
                </position>
            </language>
            <translation>
                Brave gods and women.
            </translation>
        </marginalia>
        
        <marginalia anchor_text="beatitas, siue beatitudo" hand="Italian">
            <language ident="LA">
                <position book_orientation="0" place="right_margin">
                    <marginalia_text>
                        Beatitas. beatitudo
                    </marginalia_text>
                </position>
            </language>
            <translation>
                Supreme happiness, beatitude.
            </translation>
        </marginalia>
        
        <marginalia anchor_text="Ad similitudinem enim deo propius accedebat humana virtus quàm figura" hand="Italian">
            <language ident="LA">
                <position book_orientation="0" place="right_margin">
                    <marginalia_text>
                        Ad similitudine[m] deo prope accedere debet humana virtus. quam figura.
                    </marginalia_text>
                </position>
            </language>
            <translation>
                Human virtue must be come near to the likeness of god, as does the shape.
            </translation>
        </marginalia>
        
        <marginalia anchor_text="quae negemus esse quia nunquam vidimus" hand="Italian">
            <language ident="LA">
                <position book_orientation="0" place="right_margin">
                    <marginalia_text>
                        Multa negamus esse quia nunq[uam] vidimus
                    </marginalia_text>
                </position>
            </language>
            <translation>
                We deny that there are many because we never see them.
            </translation>
        </marginalia>
        
        <marginalia anchor_text="Simia" hand="Italian"> 
            <language ident="LA">
                <position book_orientation="0" place="right_margin">
                    <marginalia_text>
                        Simia.
                    </marginalia_text>
                </position>
            </language>
            <translation>
                Monkey.
            </translation>
        </marginalia>
        
        <marginalia anchor_text="Elephanto" hand="Italian">
            <language ident="LA">
                <position book_orientation="0" place="right_margin">
                    <marginalia_text>
                        Elephantus.
                    </marginalia_text>
                </position>
            </language>
            <translation>
                Elephant.
            </translation>
        </marginalia>
        
        <marginalia anchor_text="quicquid superuacaneum sit, aut vsum non habeat, obstare" hand="Italian">
            <language ident="LA">
                <position book_orientation="0" place="right_margin">
                    <marginalia_text>
                        Quicquid sup[er]vacaneu[m] est, obstat.
                    </marginalia_text>
                </position>
            </language>
            <translation>
                Whatever is redundant hinders.
            </translation>
        </marginalia>
        
        <marginalia anchor_text="domicilia vitae" hand="Italian">
            <language ident="LA">
                <position book_orientation="0" place="right_margin">
                    <marginalia_text>
                        vita[e] Domicilia
                    </marginalia_text>
                </position>
            </language>
            <translation>
                A homely life.
            </translation>
        </marginalia>
        
        <marginalia anchor_text="ex operibus magnificis atque praeclaris" hand="Italian">
            <language ident="LA">
                <position book_orientation="0" place="right_margin">
                    <marginalia_text>
                        Ex operibus suis nosci potest.
                    </marginalia_text>
                </position>
            </language>
            <translation>
                From his works one can get to know the author. 
            </translation>
        </marginalia>
        
        <marginalia hand="Italian">
            <language ident="LA">
                <position book_orientation="0" place="right_margin">
                    <marginalia_text>
                        Vnde colligit epicurus deu[m] esse
                    </marginalia_text>
                    <person name="Epicurus"/>
                </position>
            </language>
            <translation>
                From where Epicurus gathered that god exists.
            </translation>
        </marginalia>
        
        <marginalia anchor_text="in animo insitam informationem quandam dei" hand="Italian">
            <language ident="LA">
                <position book_orientation="0" place="right_margin">
                    <marginalia_text>
                        Habemus a[n]i[m]o insita[m] Dei informationem
                    </marginalia_text>
                </position>
            </language>
            <translation>
                Through our mind we have inante information of god.
            </translation>
        </marginalia>
        
        <marginalia hand="Italian">
            <language ident="LA">
                <position book_orientation="0" place="right_margin">
                    <marginalia_text>
                        atte[n]de quò serpat.
                    </marginalia_text>
                </position>
            </language>
            <translation>
                Listen carefully to what moves slowly.
            </translation>
        </marginalia>
        
        <underline language="LA" method="pen" text="vix digna lucubratione" type="straight"/>
        <underline language="LA" method="pen" text="si impetraritis" type="straight"/>
        <underline language="LA" method="pen" text="cursus, accubitio, inclinatio, sessio, co[m]prehensio" type="straight"/>
        <underline language="LA" method="pen" text="beatus, si no[n] sit bipes" type="straight"/>
        <underline language="LA" method="pen" text="vtru[m]que omnino durum, sed vsu mollienda" type="straight"/>
        <underline language="LA" method="pen" text="vt immortalitate vincamur ab ea natura. sic" type="straight"/>
        <underline language="LA" method="pen" text="Atqui ne curiosissimi quidem homines exquirendo audire tam multa possunt, quàm sunt multa, quae" type="straight"/>
        <underline language="LA" method="pen" text="suscipimus genus hoc argumenti" type="straight"/>
        <underline language="LA" method="pen" text="omnibus his rebus obsistis" type="straight"/>
        <underline language="LA" method="pen" text="Hoc est no[n] consyderare, sed" type="straight"/>
        <underline language="LA" method="pen" text="cerebrum" type="straight"/>
        <underline language="LA" method="pen" text="cor" type="straight"/>
        <underline language="LA" method="pen" text="pulmones" type="straight"/>
        <underline language="LA" method="pen" text="iecur" type="straight"/>
        <underline language="LA" method="pen" text="temporum maturitates" type="straight"/>
        <underline language="LA" method="pen" text="mutationes vicissitudinésque cognouissent" type="straight"/>
        
        <symbol name="Jupiter" place="right_margin"/>
        <symbol name="Jupiter" place="right_margin"/>
        <symbol name="Unidentified" place="right_margin"/>
        <symbol language="LA" name="Sun" place="right_margin" text="solem"/>
        <symbol language="LA" name="Moon" place="right_margin" text="lunam"/>
        
        <mark language="LA" method="pen" name="tripunctus" place="head" text="accubitio"/>
        <mark method="pen" name="tripunctus" place="right_margin"/>
        <mark language="LA" method="pen" name="tripunctus" place="right_margin" text="Beatitas. beatitudo"/>
        
        <numeral place="left_margin">21</numeral>
        
        <drawing book_orientation="0" method="pen" place="right_margin" type="florilegium"/>
        <drawing book_orientation="0" method="pen" place="right_margin" type="florilegium"/>
        
    </annotation>
</transcription>
