<?xml version="1.0" encoding="UTF-8" standalone="no"?>
<transcription xmlns:xsi="http://www.w3.org/2001/XMLSchema-instance" xsi:noNamespaceSchemaLocation="http://www.livesandletters.ac.uk/schema/aor2_18112016.xsd">
    
    <page filename="PrincetonPA6452.030v.tif" pagination="44" reader="Harvey"/>
    <annotation>
        
        <underline language="LA" method="pen" text="Plebs et si aduersus se creatum dictatorem uidebat" type="straight"/>
        <underline language="LA" method="pen" text="cum prouocationem" type="straight"/>
        <underline language="LA" method="pen" text="nihil ex ea familia" type="straight"/>
        <underline language="LA" method="pen" text="nec superbum" type="straight"/>
        <underline language="LA" method="pen" text="discordiae intestin[a]e, bellu[m] externu[m]" type="straight"/>
        <underline language="LA" method="pen" text="magistratu egeret respublica" type="straight"/>
        <underline language="LA" method="pen" text="pax foris parta" type="straight"/>
        <underline language="LA" method="pen" text="domi impedit[ur]" type="straight"/>
        
        <symbol name="SS" place="left_margin"/>
        
        <mark method="pen" name="dash" place="right_margin"/> <!--cre-->
        
        <mark language="LA" method="pen" name="plus_sign" place="intext" text="Plebs"/>
        <mark language="LA" method="pen" name="plus_sign" place="intext" text="aduersus"/>
        <mark method="pen" name="dot" place="intext"/> <!--uidebat, tamen-->
        <mark language="LA" method="pen" name="equal_sign" place="intext" text="familia"/>
        
    </annotation>
</transcription>
