<?xml version="1.0" encoding="UTF-8" standalone="no"?>
<transcription xmlns:xsi="http://www.w3.org/2001/XMLSchema-instance" xsi:noNamespaceSchemaLocation="http://www.livesandletters.ac.uk/schema/aor2_18112016.xsd">
    
    <page filename="Newberry27495.157r.tif" reader="Harvey" signature="Oo.iii.[r]"/>
    <annotation>
        
        <marginalia anchor_text="like a tender lambe that renneth, standeth and goith alwaies by the ewes side, and moueth only as he seeth her do." hand="Italian">
            <language ident="LA">
                <position book_orientation="0" place="right_margin">
                    <marginalia_text>
                        Simile.
                    </marginalia_text>
                </position>
            </language>
            <translation>Similar.</translation>
        </marginalia>
        
        <underline language="EN" method="pen" text="powringe therinto" type="straight"/>
        <underline language="EN" method="pen" text="quiet waies" type="straight"/>
        <underline language="EN" method="pen" text="vehement persuasion" type="straight"/>
        <underline language="EN" method="pen" text="to honestie" type="straight"/>
        <underline language="EN" method="pen" text="quiet and full of rest, in" type="straight"/>
        <underline language="EN" method="pen" text="and of good proportion" type="straight"/>
        <underline language="EN" method="pen" text="agreement with him self" type="straight"/>
        <underline language="EN" method="pen" text="cleare caulmenesse" type="straight"/>
        <underline language="EN" method="pen" text="he is neuer out of pacience" type="straight"/>
        <underline language="EN" method="pen" text="most obedient to reason" type="straight"/>
        <underline language="EN" method="pen" text="vnto her all his motions" type="straight"/>
        <underline language="EN" method="pen" text="like a tender lambe that renneth, standeth and goith alwaies by the ewes side" type="straight"/>
        <underline language="EN" method="pen" text="amd moueth only as he seeth her do." type="straight"/>
        <underline language="EN" method="pen" text="This vertue therefore" type="straight"/>
        <underline language="EN" method="pen" text="requisit in Princis" type="straight"/>
        <underline language="EN" method="pen" text="arrise manie" type="straight"/>
        <underline language="EN" method="pen" text="vertues requisit" type="straight"/>
        <underline language="EN" method="pen" text="of this temperance" type="straight"/>
        <underline language="EN" method="pen" text="that riddeth the mind of affections" type="straight"/>
        <underline language="EN" method="pen" text="some Monke" type="straight"/>
        <underline language="EN" method="pen" text="is couragious" type="straight"/>
        <underline language="EN" method="pen" text="freeharted and of prowesse" type="straight"/>
        <underline language="EN" method="pen" text="whatsoeuer is done" type="straight"/>
        <underline language="EN" method="pen" text="haue angre, hatred, good will, disdeigne, lust nor any affeccion in" type="straight"/>
        <underline language="EN" method="pen" text="authoritie emonge" type="straight"/>
        <underline language="EN" method="pen" text="ridd and roote oute" type="straight"/>
        <underline language="EN" method="pen" text="mindes, affections" type="straight"/>
        <underline language="EN" method="pen" text="well so to do" type="straight"/>
        <underline language="EN" method="pen" text="affections some partes good" type="straight"/>
        <underline language="EN" method="pen" text="corrupt and striuing" type="straight"/>
        <underline language="EN" method="pen" text="against honestie" type="straight"/>
        <underline language="EN" method="pen" text="obey vnto reason" type="straight"/>
        <underline language="EN" method="pen" text="roote vp affections cleane" type="straight"/>
        <underline language="EN" method="pen" text="an act established" type="straight"/>
        <underline language="EN" method="pen" text="shoulde drinke wine" type="straight"/>
        <underline language="EN" method="pen" text="a fall" type="straight"/>
        <underline language="EN" method="pen" text="forbed renning" type="straight"/>
        <underline language="EN" method="pen" text="breake horses" type="straight"/>
        
        <symbol name="SS" place="head"/>
        
        <mark language="EN" method="pen" name="bracket" place="left_margin" text="like a tender lambe that renneth, standeth and goith alwaies by the ewes side, and moueth only as he seeth her do."/>
        <mark method="pen" name="vertical_bar" place="left_margin"/>
        <mark method="pen" name="vertical_bar" place="left_margin"/>
        
        <mark language="EN" method="pen" name="bracket" place="right_margin" text="like a tender lambe that renneth, standeth and goith alwaies by the ewes side, and moueth only as he seeth her do."/>
        <mark method="pen" name="X_sign" place="right_margin"/>
        <!-- unknown mark --> <!--JG: sort of 'u', next to "which in af-"-->
        <mark method="pen" name="X_sign" place="right_margin"/>
        <mark method="pen" name="X_sign" place="right_margin"/>
        <mark method="pen" name="X_sign" place="right_margin"/>
        
        <mark method="pen" name="dot" place="intext"/> <!-- resistance, like -->
        <mark method="pen" name="dot" place="intext"/> <!-- feates, for -->
        <mark method="pen" name="dot" place="intext"/> <!-- do, bicause -->
        
        <mark method="pen" name="plus_sign" place="tail"/>
        
    </annotation>
</transcription>
