<?xml version="1.0" encoding="UTF-8" standalone="no"?>
<transcription xmlns:xsi="http://www.w3.org/2001/XMLSchema-instance" xsi:noNamespaceSchemaLocation="http://www.livesandletters.ac.uk/schema/aor2_18112016.xsd">
    
    <page filename="Newberry27495.174v.tif" reader="Harvey" signature="[Ss.iiii.[v]]"/>
    <annotation>
        
        <underline language="EN" method="chalk" text="it hath bine said the other night) Loue frameth not with olde men, and the trickes that in yonge men be galauntnesse, courtesie              and precisenesse so acceptable to women, in" type="straight"/>
        <underline language="EN" method="pen" text="galauntnesse" type="straight"/>
        <underline language="EN" method="pen" text="courtesie" type="straight"/>
        <underline language="EN" method="pen" text="precisenesse so acceptable" type="straight"/>
        <underline language="EN" method="pen" text="meere folies and fondnesse to be" type="straight"/>
        <underline language="EN" method="pen" text="them hatred of women" type="straight"/>
        <underline language="EN" method="pen" text="mockes" type="straight"/>
        <underline language="EN" method="pen" text="Aristotel an" type="straight"/>
        <underline language="EN" method="pen" text="louer" type="straight"/>
        <underline language="EN" method="pen" text="louers do" type="straight"/>
        <underline language="EN" method="pen" text="forgete to teach his Prince" type="straight"/>
        <underline language="EN" method="pen" text="boyes would mocke him" type="straight"/>
        <underline language="EN" method="pen" text="wome[n] would" type="straight"/>
        <underline language="EN" method="pen" text="iesting stocke" type="straight"/>
        <underline language="EN" method="pen" text="happinesse to loue" type="straight"/>
        <underline language="EN" method="pen" text="take this loue form him" type="straight"/>
        <underline language="EN" method="pen" text="perfection ouer and aboue" type="straight"/>
        <underline language="EN" method="pen" text="happilie out of miserie and" type="straight"/>
        <underline language="EN" method="pen" text="Peter Bembo" type="straight"/>
        <underline language="EN" method="pen" text="some louers" type="straight"/>
        <underline language="EN" method="pen" text="the debates and tourmentes" type="straight"/>
        <underline language="EN" method="pen" text="Ladies" type="straight"/>
        <underline language="EN" method="pen" text="sweete?" type="straight"/>
        <underline language="EN" method="chalk" text="were kendled with those" type="straight"/>
        <underline language="EN" method="pen" text="kendled with those" type="straight"/>
        <underline language="EN" method="pen" text="beeing wise" type="straight"/>
        <underline language="EN" method="pen" text="perhappes loue after a sorte" type="straight"/>
        <underline language="EN" method="pen" text="muche praise and great happinesse" type="straight"/>
        <underline language="EN" method="pen" text="teachinge of his Prince" type="straight"/>
        <underline language="EN" method="pen" text="commit any thinge" type="straight"/>
        
        <symbol name="SS" place="left_margin"/>
        
        <mark method="pen" name="quotation_mark" place="head"/>
        
        <mark method="pen" name="quotation_mark" place="left_margin"/>
        <mark method="pen" name="quotation_mark" place="left_margin"/>
        <mark method="pen" name="plus_sign" place="left_margin"/>
        
        <mark method="pen" name="dot" place="intext"/> <!-- women, in -->
        <mark method="pen" name="dot" place="intext"/> <!-- backe, and -->
        <mark method="pen" name="dot" place="intext"/> <!-- olde, me -->
        <mark method="pen" name="dot" place="intext"/> <!-- loue, to -->
        
    </annotation>
</transcription>
