<?xml version="1.0" encoding="UTF-8" standalone="no"?>
<transcription xmlns:xsi="http://www.w3.org/2001/XMLSchema-instance" xsi:noNamespaceSchemaLocation="http://www.livesandletters.ac.uk/schema/aor2_18112016.xsd">
    
    <page filename="Newberry27495.181r.tif" reader="Harvey" signature="V.iii.[r]"/> <!-- AB: Signature contains a printer's error, should be Vv.iii.[r]. -->
    <annotation>
        
        <underline language="EN" method="pen" text="noble condicions" type="straight"/>
        <underline language="EN" method="chalk" text="is a ware that his eyes snatch" type="straight"/>
        <underline language="EN" method="chalk" text="to beehoulde" type="straight"/>
        <underline language="EN" method="chalk" text="the influence" type="straight"/>
        <underline language="EN" method="chalk" text="and litle" type="straight"/>
        <underline language="EN" method="chalk" text="those liuelye spirites, that twinkle out throughe" type="straight"/>
        <underline language="EN" method="chalk" text="put continually freshe nourishment to the fire" type="straight"/>
        <underline language="EN" method="pen" text="vp reason" type="straight"/>
        <underline language="EN" method="chalk" text="to fense the fortresse" type="straight"/>
        <underline language="EN" method="pen" text="to fense the fortresse" type="straight"/>
        <underline language="EN" method="pen" text="his hart" type="straight"/>
        <underline language="EN" method="chalk" text="wise the passages against sense and appetites" type="straight"/>
        <underline language="EN" method="pen" text="entre neyther with" type="straight"/>
        <underline language="EN" method="pen" text="subtill practise" type="straight"/>
        <underline language="EN" method="pen" text="throughlye all filthinesse" type="straight"/>
        <underline language="EN" method="pen" text="commune loue" type="straight"/>
        <underline language="EN" method="pen" text="the holye way of loue" type="straight"/>
        <underline language="EN" method="pen" text="guide of reason" type="straight"/>
        <underline language="EN" method="pen" text="that the body" type="straight"/>
        <underline language="EN" method="pen" text="bicause beautie" type="straight"/>
        <underline language="EN" method="chalk" text="an heauenlie shyning beame" type="straight"/>
        <underline language="EN" method="pen" text="heauenlie shyning beame" type="straight"/>
        <underline language="EN" method="pen" text="cleane sundred frome it, is most perfect" type="straight"/>
        <underline language="EN" method="chalk" text="as a mann heareth not with his mouth" type="straight"/>
        <underline language="EN" method="pen" text="with feelynge" type="straight"/>
        <underline language="EN" method="pen" text="beawtie is the verye butt to leuell" type="straight"/>
        <underline language="EN" method="chalk" text="verye butt to leuell" type="straight"/>
        <underline language="EN" method="pen" text="vertue of seeinge." type="straight"/>
        <underline language="EN" method="pen" text="blinde iudgemente" type="straight"/>
        <underline language="EN" method="pen" text="eyes the bryghtnesse, the comelynesse" type="straight"/>
        <underline language="EN" method="pen" text="sparkles, laughters, gestures and all the other" type="straight"/>
        
        <underline language="EN" method="pen" text="Beawtye" type="straight"/>
        <underline language="EN" method="pen" text="most perfect" type="straight"/>

        <symbol language="EN" name="SS" place="right_margin" text="eyes, the bryghtnesse, the comelynesse"/>
        
        <mark method="pen" name="plus_sign" place="left_margin"/>
        <mark method="pen" name="bracket" place="left_margin"/>
        
        <mark method="pen" name="quotation_mark" place="right_margin"/>
        <mark method="pen" name="X_sign" place="right_margin"/>
        <mark method="pen" name="quotation_mark" place="right_margin"/>
        <mark language="EN" method="pen" name="plus_sign" place="right_margin" text="beawtie is the verye butt to leuell"/>
        
        <mark method="pen" name="dot" place="intext"/> <!-- reason, and -->
        <mark method="pen" name="dot" place="intext"/> <!-- corruption, bicause -->
        <mark method="pen" name="dot" place="intext"/> <!-- sense, and -->
        <mark language="EN" method="pen" name="plus_sign" place="intext" text="eyes"/>
        
    </annotation>
</transcription>
