<?xml version="1.0" encoding="UTF-8" standalone="no"?>
<transcription xmlns:xsi="http://www.w3.org/2001/XMLSchema-instance" xsi:noNamespaceSchemaLocation="http://www.livesandletters.ac.uk/schema/aor2_18112016.xsd">
    <page filename="RCP7134.221v.tif" pagination="[214v]" reader="John Dee" signature="[HH ij[v]]"/>
    <annotation>
        
        <marginalia anchor_text="fortuitis eventibus" hand="English_secretary">
            <language ident="LA">
                <position book_orientation="0" place="left_margin">
                    <marginalia_text>fortuiti eve[n]tus</marginalia_text>
                </position>
            </language>
            <translation>Fortuitous events.</translation>
        </marginalia>
        
    </annotation>
</transcription>
