<?xml version="1.0" encoding="UTF-8" standalone="no"?>
<transcription xmlns:xsi="http://www.w3.org/2001/XMLSchema-instance" xsi:noNamespaceSchemaLocation="http://www.livesandletters.ac.uk/schema/aor2_18112016.xsd">
    
    <page filename="ChChWb512.101v.tif" reader="Dee"/>
    <annotation>
        
        <marginalia hand="English_secretary">
            <language ident="LA">
                <position book_orientation="0" place="left_margin">
                    <marginalia_text>
                        2100 monachos in vno monasterio habitare.  <!-- NBW: This is likely a syncopated perfect -->
                    </marginalia_text>
                </position>
            </language>
            <translation>2100 monks lived in one monastery.</translation>
        </marginalia>
        
    </annotation>
</transcription>
